kwamehealthtoolboxpublic/__init__.py
kwamehealthtoolboxpublic/createDocument.py
kwamehealthtoolboxpublic/getDateTime.py
kwamehealthtoolboxpublic/sendEmail.py
kwamehealthtoolboxpublic-1.3.2.dist-info/METADATA
kwamehealthtoolboxpublic-1.3.2.dist-info/WHEEL
kwamehealthtoolboxpublic-1.3.2.dist-info/top_level.txt
kwamehealthtoolboxpublic-1.3.2.dist-info/RECORD
