Metadata-Version: 2.1
Name: kwamehealthtoolboxpublic
Version: 1.3.2
Summary: Toolbox with custom functions
Home-page: https://github.com/Kwame-Health/khtoolbox
Author: Panashe Madzudzo
Author-email: admin@kwame.health
License: UNKNOWN
Project-URL: Bug Tracker, https://github.com/Kwame-Health/khtoolbox/issues
Platform: UNKNOWN
Requires-Dist: requests
Requires-Dist: urllib3
Requires-Dist: twilio
Requires-Dist: pytz
Requires-Dist: boto3
Requires-Dist: convertapi
